arit777/__init__.py
arit777/module1.py
arit777-0.1.dist-info/licenses/AUTHORS.md
arit777-0.1.dist-info/licenses/LICENSE
arit777-0.1.dist-info/METADATA
arit777-0.1.dist-info/WHEEL
arit777-0.1.dist-info/top_level.txt
arit777-0.1.dist-info/RECORD
