Metadata-Version: 2.4
Name: arit777
Version: 0.1
Summary: This is a prototype package for generating rules from raw text
Author: Olegs Verhodubs
Author-email: oleg.verhodub@inbox.lv
License: Apache-2.0
Classifier: Programming Language :: Python :: 3.13
Classifier: License :: OSI Approved :: Apache Software License
Classifier: Operating System :: OS Independent
Requires-Python: >=3.13
License-File: LICENSE
License-File: AUTHORS.md
Dynamic: author
Dynamic: author-email
Dynamic: classifier
Dynamic: description
Dynamic: description-content-type
Dynamic: license
Dynamic: license-file
Dynamic: requires-python
Dynamic: summary
